{
  "metainfo" : {
    "type" : "Databricks",
    "fabricId" : "370",
    "jobId" : "jobs/Dbx_job",
    "name" : "Dbx_job",
    "schedule" : "None",
    "scheduleTimeZone" : "UTC",
    "jobClusterMode" : {
      "clusterMode" : "Single"
    },
    "enabled" : false,
    "defaultClusterSize" : "3.4.1_spark_small_job",
    "alerting" : {
      "emails" : "",
      "onStart" : false,
      "onSuccess" : false,
      "onFailure" : false
    },
    "maxConcurrentRuns" : 1,
    "processDefaultSettings" : {
      "type" : "Inherited",
      "retries" : 0,
      "alerting" : {
        "emails" : "",
        "onStart" : false,
        "onSuccess" : false,
        "onFailure" : false
      }
    },
    "availableFabrics" : [ {
      "id" : "2284",
      "name" : "Databricks_fabric",
      "clusterSizes" : {
        "default" : "small",
        "availableClusterSizes" : [ "small" ]
      },
      "pylibsResolutionMode" : {
        "PublicCentral" : { }
      },
      "scalalibsResolutionMode" : {
        "PublicCentral" : { }
      }
    }, {
      "id" : "2462",
      "name" : "Databricks_UC_Fabric",
      "clusterSizes" : {
        "default" : "small",
        "availableClusterSizes" : [ "small" ]
      },
      "pylibsResolutionMode" : {
        "PublicCentral" : { }
      },
      "scalalibsResolutionMode" : {
        "PublicCentral" : { }
      }
    }, {
      "id" : "2369",
      "name" : "PM",
      "clusterSizes" : {
        "default" : "small",
        "availableClusterSizes" : [ "small" ]
      },
      "pylibsResolutionMode" : {
        "PublicCentral" : { }
      },
      "scalalibsResolutionMode" : {
        "PublicCentral" : { }
      }
    }, {
      "id" : "2333",
      "name" : "Databricks_non_admin_fabric",
      "clusterSizes" : {
        "default" : "small",
        "availableClusterSizes" : [ "small" ]
      },
      "pylibsResolutionMode" : {
        "PublicCentral" : { }
      },
      "scalalibsResolutionMode" : {
        "PublicCentral" : { }
      }
    }, {
      "id" : "370",
      "name" : "databricks_fabric_13_3_LTS",
      "clusterSizes" : {
        "default" : "3.4.1_spark_small_job",
        "availableClusterSizes" : [ "3.4.1_spark_small_job", "12_2_LTS_JOB", "hashi_vault" ]
      },
      "pylibsResolutionMode" : {
        "PublicCentral" : { }
      },
      "scalalibsResolutionMode" : {
        "PublicCentral" : { }
      }
    } ]
  },
  "processes" : {
    "xMGwu9lXTvORXjmsaw96Y$$9Iw9T-0CqSKUzGnu8PnjB" : {
      "id" : "xMGwu9lXTvORXjmsaw96Y$$9Iw9T-0CqSKUzGnu8PnjB",
      "component" : "Pipeline",
      "metadata" : {
        "label" : "Pipeline_0",
        "slug" : "Pipeline_0",
        "x" : -180,
        "y" : -200
      },
      "ports" : {
        "inputs" : [ {
          "id" : "L2-dfnlPc19KuUxseDYkv$$6SI0rbmb0CDgga3oySwdB",
          "slug" : ""
        } ],
        "outputs" : [ {
          "id" : "gJXrjEMttU3LxKmU7l0Hh$$jQf2A946dccXJYpDGkjEJ",
          "slug" : ""
        } ]
      },
      "settings" : {
        "type" : "Inherited",
        "alerting" : {
          "emails" : "",
          "onStart" : false,
          "onSuccess" : false,
          "onFailure" : false
        }
      },
      "properties" : {
        "pipelineId" : "pipelines/SecondPipeline",
        "configurations" : {
          "schema" : [ {
            "name" : "JDBC_URL",
            "optional" : false,
            "kind" : {
              "type" : "string",
              "value" : "jdbc:mysql://3.101.152.38:3306/test_database"
            },
            "isReferenced" : false,
            "isWorkflowNodeConfiguration" : false
          }, {
            "name" : "JDBC_TABLE",
            "optional" : false,
            "kind" : {
              "type" : "string",
              "value" : "test_table_automation"
            },
            "isReferenced" : false,
            "isWorkflowNodeConfiguration" : false
          }, {
            "name" : "JDBC",
            "optional" : false,
            "kind" : {
              "type" : "string",
              "value" : "jdbc:mysql://3.101.152.38:3306/"
            },
            "isReferenced" : false,
            "isWorkflowNodeConfiguration" : false
          }, {
            "name" : "JDBC_DATABASE",
            "optional" : false,
            "kind" : {
              "type" : "string",
              "value" : "test_database"
            },
            "isReferenced" : false,
            "isWorkflowNodeConfiguration" : false
          }, {
            "name" : "DRIVER_NAME",
            "optional" : false,
            "kind" : {
              "type" : "string",
              "value" : "com.mysql.jdbc.Driver"
            },
            "isReferenced" : false,
            "isWorkflowNodeConfiguration" : false
          }, {
            "name" : "JDBC_USER_SECRET",
            "optional" : false,
            "kind" : {
              "type" : "databricks_secret",
              "value" : "rohit_mysql:username"
            },
            "isReferenced" : false,
            "isWorkflowNodeConfiguration" : false
          }, {
            "name" : "JDBC_PASSWORD_SECRET",
            "optional" : false,
            "kind" : {
              "type" : "databricks_secret",
              "value" : "rohit_mysql:password"
            },
            "isReferenced" : false,
            "isWorkflowNodeConfiguration" : false
          }, {
            "name" : "JDBC_USER_STRING",
            "optional" : false,
            "kind" : {
              "type" : "string",
              "value" : "test_user"
            },
            "isReferenced" : false,
            "isWorkflowNodeConfiguration" : false
          }, {
            "name" : "JDBC_PASSWORD_STRING",
            "optional" : false,
            "kind" : {
              "type" : "string",
              "value" : "admin"
            },
            "isReferenced" : false,
            "isWorkflowNodeConfiguration" : false
          }, {
            "name" : "ENV_JDBC_USERNAME",
            "optional" : false,
            "kind" : {
              "type" : "string",
              "value" : "JDBC_USERNAME"
            },
            "isReferenced" : false,
            "isWorkflowNodeConfiguration" : false
          }, {
            "name" : "ENV_JDBC_PASSWORD",
            "optional" : false,
            "kind" : {
              "type" : "string",
              "value" : "JDBC_PASSWORD"
            },
            "isReferenced" : false,
            "isWorkflowNodeConfiguration" : false
          }, {
            "name" : "TEST",
            "optional" : false,
            "kind" : {
              "type" : "string",
              "value" : "test"
            },
            "isReferenced" : false,
            "isWorkflowNodeConfiguration" : false
          }, {
            "name" : "ADM",
            "optional" : false,
            "kind" : {
              "type" : "string",
              "value" : "adm"
            },
            "isReferenced" : false,
            "isWorkflowNodeConfiguration" : false
          }, {
            "name" : "IN",
            "optional" : false,
            "kind" : {
              "type" : "string",
              "value" : "in"
            },
            "isReferenced" : false,
            "isWorkflowNodeConfiguration" : false
          }, {
            "name" : "JDBC_DEST_TABLE",
            "optional" : false,
            "kind" : {
              "type" : "string",
              "value" : "test_table_destination"
            },
            "isReferenced" : false,
            "isWorkflowNodeConfiguration" : false
          }, {
            "name" : "USER",
            "optional" : false,
            "kind" : {
              "type" : "string",
              "value" : "user"
            },
            "isReferenced" : false,
            "isWorkflowNodeConfiguration" : false
          } ],
          "instances" : {
            "JDBC_imported_python" : [ "default" ]
          },
          "overrides" : { },
          "selectedInstance" : "default"
        }
      }
    }
  },
  "connections" : [ ]
}