{
  "id" : "model1",
  "metainfo" : {
    "label" : "model1",
    "autoLayout" : false,
    "staleState" : "none",
    "sourceSuggestions" : {
      "sources" : [ ]
    }
  },
  "processes" : {
    "model1##zckQXpPC" : {
      "id" : "model1##zckQXpPC",
      "component" : "TargetModel",
      "metadata" : {
        "label" : "model1",
        "x" : 120,
        "y" : 120,
        "phase" : 0,
        "macroDependencies" : [ ]
      },
      "properties" : {
        "customQueryDisabled" : true,
        "customQuery" : false,
        "incrementalEditorDisabled" : true,
        "query" : "SELECT * \n\nFROM newSeed\n",
        "incrementalKey" : false,
        "incremental" : {
          "expression" : "true"
        }
      },
      "ports" : {
        "inputs" : [ {
          "id" : "XopsZE4z",
          "schema" : {
            "providerType" : "Databricks",
            "fields" : [ {
              "name" : "id",
              "dataType" : {
                "type" : "Integer"
              }
            }, {
              "name" : "first_name",
              "dataType" : {
                "type" : "String"
              }
            }, {
              "name" : "last_name",
              "dataType" : {
                "type" : "String"
              }
            } ]
          },
          "slug" : "newSeed"
        } ],
        "outputs" : [ {
          "id" : "hLLW3bwy",
          "schema" : {
            "providerType" : "Databricks",
            "fields" : [ {
              "name" : "id",
              "dataType" : {
                "type" : "Integer"
              }
            }, {
              "name" : "first_name",
              "dataType" : {
                "type" : "String"
              }
            }, {
              "name" : "last_name",
              "dataType" : {
                "type" : "String"
              }
            } ]
          },
          "slug" : "out"
        } ],
        "isCustomOutputSchema" : false
      }
    },
    "CCxbypv7up5TK6RoILkYs" : {
      "id" : "CCxbypv7up5TK6RoILkYs",
      "component" : "Seed",
      "metadata" : {
        "label" : "newSeed",
        "slug" : "newSeed",
        "x" : 0,
        "y" : 120,
        "phase" : 0
      },
      "properties" : {
        "table" : {
          "name" : "newSeed",
          "sourceType" : "Seed",
          "alias" : ""
        }
      },
      "ports" : {
        "inputs" : [ ],
        "outputs" : [ {
          "id" : "5lD90Y4TQoaIUXJb7XZAB",
          "schema" : {
            "providerType" : "Databricks",
            "fields" : [ {
              "name" : "id",
              "dataType" : {
                "type" : "Integer"
              }
            }, {
              "name" : "first_name",
              "dataType" : {
                "type" : "String"
              }
            }, {
              "name" : "last_name",
              "dataType" : {
                "type" : "String"
              }
            } ]
          },
          "slug" : "out"
        } ],
        "isCustomOutputSchema" : false
      }
    }
  },
  "connections" : [ {
    "id" : "TVlHreQk19FFCexfB0VQT$$iB4I2SwB_FLUe9Z7tLUP6",
    "source" : "CCxbypv7up5TK6RoILkYs",
    "sourcePort" : "5lD90Y4TQoaIUXJb7XZAB",
    "target" : "model1##zckQXpPC",
    "targetPort" : "XopsZE4z"
  } ],
  "component" : "Model"
}