{
  "metainfo" : {
    "id" : "1",
    "uri" : "pipelines/workflow",
    "language" : "python",
    "fabricId" : "3461",
    "frontEndLanguage" : "sql",
    "mode" : "batch",
    "udfs" : {
      "language" : "python",
      "udfs" : [ ],
      "functionPackageName" : "abhishekse2etestsprophecy.io_team.deletepipflow.functions",
      "sharedFunctionPackageNames" : [ ]
    },
    "udafs" : {
      "language" : "python",
      "code" : ""
    },
    "configuration" : {
      "common" : {
        "type" : "record",
        "fields" : [ ]
      },
      "oldCommon" : {
        "type" : "record",
        "fields" : [ ]
      },
      "fabrics" : { },
      "instances" : { },
      "selected" : "default",
      "nonEditable" : [ ],
      "isSubscribedPipelineWithPipelineConfigs" : false
    },
    "sparkConf" : [ ],
    "hadoopConf" : [ ],
    "codeMode" : "sparse",
    "buildSystem" : "maven",
    "externalDependencies" : [ ],
    "dependentProjectExternalDependencies" : [ ],
    "isImported" : false,
    "interimMode" : "Full",
    "interimModeEnabled" : true,
    "visualCodeInterimMode" : "Disabled",
    "recordsLimit" : {
      "enabled" : false,
      "value" : 1000
    },
    "topLevelPackage" : "p2",
    "configurationVersion" : "v1"
  },
  "connections" : [ ],
  "processes" : {
    "J4QHlBJzlWnqltgfsufGe$$AnpPoAJUYvAwsCg_rP9Rb" : {
      "id" : "J4QHlBJzlWnqltgfsufGe$$AnpPoAJUYvAwsCg_rP9Rb",
      "component" : "Source",
      "metadata" : {
        "label" : "Source_0",
        "slug" : "Source_0",
        "x" : 140,
        "y" : 160,
        "phase" : 0,
        "cache" : false,
        "detailedStats" : false,
        "isImported" : false
      },
      "ports" : {
        "inputs" : [ ],
        "outputs" : [ {
          "id" : "IhfngcYy9oBtRw_i1eoV-$$dIMkQyeE2EGpxmEWVUQSt",
          "slug" : "out"
        } ],
        "selectedInputFields" : [ ],
        "isCustomOutputSchema" : false
      },
      "properties" : { }
    }
  },
  "ports" : {
    "inputs" : [ ],
    "outputs" : [ ],
    "selectedInputFields" : [ ],
    "isCustomOutputSchema" : false
  },
  "diagnostics" : [ {
    "property" : "$.workflow.processes.J4QHlBJzlWnqltgfsufGe$$AnpPoAJUYvAwsCg_rP9Rb.properties.datasetId",
    "range" : {
      "start" : {
        "line" : 0,
        "character" : 0
      },
      "end" : {
        "line" : 0,
        "character" : 0
      }
    },
    "severity" : 1,
    "message" : "dataset id missing",
    "tags" : [ ],
    "relatedInformation" : [ ]
  } ]
}