{"textPassword":null,"refreshKrb5Config":null,"keytab":null,"format":"jdbc","cascadeTruncate":null,"lowerBound":null,"writeMode":"overwrite","description":"","preSQL":null,"customSchema":null,"postSQL":null,"partitionColumn":null,"pushDownPredicate":true,"truncate":null,"batchsize":null,"query":null,"sessionInitStatement":null,"isolationLevel":null,"readFromSource":"dbtable","credentialScope":"rohit_mysql","upperBound":null,"pushDownAggregate":null,"schema":{"type":"struct","fields":[{"name":"a","type":"integer","nullable":true,"metadata":{"description":"","mappings":[],"tags":[]}}]},"driver":"${DRIVER_NAME}","createTableColumnTypes":null,"jdbcUrl":"${JDBC_URL}","fetchsize":null,"dbtable":"test_table_destination","componentInfo":{"gemId":"gitUri=http://gitserver:3000/9gt3CHHz_team_9/pJIIcs5r_project_39.git&subPath=&tag=0.0.6&projectSubscriptionProjectId=39&path=gems/jdbc","projectName":"ProphecySparkBasicsScala"},"principal":null,"textUsername":null,"createTableOptions":null,"queryTimeout":null,"numPartitions":null,"datasetType":"Warehouse","credType":"databricksSecrets"}